<?xml version="1.0" encoding="UTF-8" standalone="no"?><mnemosyne>


<deck id="1"><name>yasmin</name><information>fsfdsff</information><strategy>ffff</strategy><qtdCards>90</qtdCards></deck><card type="character"><name>yasmon</name><information>sdsdfsdf</information><cost>none</cost><power>1</power><defense>1</defense><image>btnCard1</image><ability>Aumenta 10 pontos de Força desta carta</ability><target>OWNER</target><oper>INCREMENT</oper><no>10</no><event type="changePower"/><ability>Aumenta 10 pontos de Defesa de outra carta do Jogador</ability><target>TARGETCREATURE</target><oper>INCREMENT</oper><no>10</no><event type="changeDefense"/><ability>Diminui 10 pontos dos Pontos de Vida do Oponente</ability><target>OPPONENT</target><oper>DECREMENT</oper><no>10</no><event type="changeScore"/></card><card type="character"><name>carlos</name><information>fdfdsfsdfs</information><cost>none</cost><power>99</power><defense>99</defense><image>btnCard2</image><ability>Diminui 20 pontos de Força desta carta</ability><target>OWNER</target><oper>DECREMENT</oper><no>20</no><event type="changePower"/><ability>Diminui 20 pontos de Defesa do Jogador</ability><target>PLAYER</target><oper>DECREMENT</oper><no>20</no><event type="changeDefense"/><ability>Aumenta 20 pontos dos Pontos de Vida do Oponente</ability><target>OPPONENT</target><oper>INCREMENT</oper><no>20</no><event type="changeScore"/></card><card type="character"><name>carlos</name><information>fdfdsfsdfs</information><cost>none</cost><power>99</power><defense>99</defense><image>btnCard2</image><ability>Diminui 20 pontos de Força desta carta</ability><target>OWNER</target><oper>DECREMENT</oper><no>20</no><event type="changePower"/><ability>Diminui 20 pontos de Defesa do Jogador</ability><target>PLAYER</target><oper>DECREMENT</oper><no>20</no><event type="changeDefense"/><ability>Aumenta 20 pontos dos Pontos de Vida do Oponente</ability><target>OPPONENT</target><oper>INCREMENT</oper><no>20</no><event type="changeScore"/></card></mnemosyne>